EJERCICIO1/ejercicio1.v
module contador(input wire clk, reset, enable, loadbit, input wire[11:0] load ,output reg [11:0]cont);
  always @ (posedge clk or posedge reset or posedge loadbit) begin
  if (reset)
    cont <= 12'b000000000000;
  else if (loadbit)
      cont <= load;
  else if (enable)
      cont <= cont + 12'b1;
  end
endmodule

module ROM(input wire[11:0] A, output  wire[7:0] Y);
  assign Y = Memoria[A];
  reg[7:0] Memoria[0:4095];
  initial begin
    $readmemb("Memoria.list", Memoria);
  end
endmodule


module FFFLETCH(input wire clk, reset, enable, input wire [7:0]A, output reg[3:0] Y, output reg[3:0] Y1);
 always @ (posedge clk or posedge reset) begin
    if (reset)
      Y <= 7'b00000000;
    else if(enable)
      Y <= A[3:0];
      Y1 <= A[7:4];
  end
endmodule

module CONJ(input wire clk, reset, enable, loadbit, input wire[11:0] load, enable1, output wire[3:0] Y, Y1);
  wire[11:0] A;
  wire[7:0] B;
  contador C1(clk, reset, enable, loadbit, load, A);
  ROM C2(A, B);
  FFFLETCH C3(clk, reset, enable1, B, Y, Y1);
endmodule

EJERCICIO1/ejercicio1_tb.v
module testbench();
reg clk, reset, enable, loadbit, enable1;
reg[11:0] load;
wire[3:0] Y, Y1;
CONJ C4(clk, reset, enable, loadbit, load, enable1, Y, Y1);

always
  #5 clk <= ~clk;

initial begin
  $display("uP");
  $display("clk reset enable loadbit load enable1 | Y Y1");
  $display("-----------|---------");
  $monitor("%b %b %b %b %b %b | %b %b", clk, reset, enable, loadbit, load, enable1, Y1, Y);
      clk = 0; reset = 0; enable = 0; loadbit = 0; load = 12'b000000000000; enable1 = 0;
  #1  reset = 1; enable = 1; loadbit = 0; load = 12'b000000000000; enable1 = 1;
  #1  reset = 0; enable = 1; loadbit = 0; load = 12'b000000000000; enable1 = 1;
  #1  reset = 0; enable = 1; loadbit = 0; load = 12'b000000000000; enable1 = 1;
  #1  reset = 0; enable = 1; loadbit = 0; load = 12'b000000000000; enable1 = 1;
  #1  reset = 0; enable = 1; loadbit = 0; load = 12'b000000000000; enable1 = 1;
  #1  reset = 0; enable = 1; loadbit = 0; load = 12'b000000000000; enable1 = 1;
  #1  reset = 0; enable = 1; loadbit = 0; load = 12'b000000000000; enable1 = 1;
  #1  reset = 0; enable = 1; loadbit = 0; load = 12'b000000000000; enable1 = 1;
  #1  reset = 0; enable = 1; loadbit = 0; load = 12'b000000000000; enable1 = 1;
  #1  reset = 0; enable = 1; loadbit = 0; load = 12'b000000000000; enable1 = 1;
  #1  reset = 0; enable = 1; loadbit = 0; load = 12'b000000000000; enable1 = 1;
  #1  reset = 0; enable = 1; loadbit = 0; load = 12'b000000000000; enable1 = 1;
  #1  reset = 0; enable = 1; loadbit = 0; load = 12'b000000000000; enable1 = 1;
  #1  reset = 0; enable = 1; loadbit = 0; load = 12'b000000000000; enable1 = 1;
  #1  reset = 0; enable = 1; loadbit = 0; load = 12'b000000000000; enable1 = 1;
  #1  reset = 0; enable = 1; loadbit = 0; load = 12'b000000000000; enable1 = 1;
  #1  reset = 0; enable = 1; loadbit = 0; load = 12'b000000000000; enable1 = 1;
  #1  reset = 0; enable = 1; loadbit = 0; load = 12'b000000000000; enable1 = 1;
  #1  reset = 0; enable = 1; loadbit = 0; load = 12'b000000000000; enable1 = 1;
  #1  reset = 0; enable = 1; loadbit = 0; load = 12'b000000000000; enable1 = 1;
  #1  reset = 0; enable = 1; loadbit = 0; load = 12'b000000000000; enable1 = 1;
  #1  reset = 0; enable = 1; loadbit = 0; load = 12'b000000000000; enable1 = 1;
  #1  reset = 0; enable = 1; loadbit = 0; load = 12'b000000000000; enable1 = 1;
  #1  reset = 0; enable = 1; loadbit = 0; load = 12'b000000000000; enable1 = 1;
  #1  reset = 0; enable = 1; loadbit = 0; load = 12'b000000000000; enable1 = 1;
  #1  reset = 0; enable = 1; loadbit = 0; load = 12'b000000000000; enable1 = 1;
  #1  reset = 0; enable = 1; loadbit = 0; load = 12'b000000000000; enable1 = 1;
  #1  reset = 0; enable = 1; loadbit = 0; load = 12'b000000000000; enable1 = 1;
  #1  reset = 0; enable = 1; loadbit = 0; load = 12'b000000000000; enable1 = 1;
  #1  reset = 0; enable = 1; loadbit = 0; load = 12'b000000000000; enable1 = 1;
  #1  reset = 0; enable = 1; loadbit = 0; load = 12'b000000000000; enable1 = 1;
  #1  reset = 0; enable = 1; loadbit = 0; load = 12'b000000000000; enable1 = 1;
  #1  reset = 0; enable = 1; loadbit = 0; load = 12'b000000000000; enable1 = 1;
  #1  reset = 0; enable = 1; loadbit = 0; load = 12'b000000000000; enable1 = 1;
  #1  reset = 0; enable = 1; loadbit = 0; load = 12'b000000000000; enable1 = 1;
  #1  reset = 0; enable = 1; loadbit = 0; load = 12'b000000000000; enable1 = 1;
  #1  reset = 0; enable = 1; loadbit = 0; load = 12'b000000000000; enable1 = 1;
  #1  reset = 0; enable = 1; loadbit = 0; load = 12'b000000000000; enable1 = 1;
  #1  reset = 0; enable = 1; loadbit = 0; load = 12'b000000000000; enable1 = 1;
  #1  reset = 0; enable = 1; loadbit = 0; load = 12'b000000000000; enable1 = 1;
  #1  reset = 0; enable = 1; loadbit = 0; load = 12'b000000000000; enable1 = 1;
  #1  reset = 0; enable = 1; loadbit = 0; load = 12'b000000000000; enable1 = 1;
  #1  reset = 0; enable = 1; loadbit = 0; load = 12'b000000000000; enable1 = 1;
  #1  reset = 0; enable = 1; loadbit = 0; load = 12'b000000000000; enable1 = 1;
  #1  reset = 0; enable = 1; loadbit = 0; load = 12'b000000000000; enable1 = 1;
  #1  reset = 0; enable = 1; loadbit = 0; load = 12'b000000000000; enable1 = 1;
  #1  reset = 0; enable = 1; loadbit = 0; load = 12'b000000000000; enable1 = 1;
  #1  reset = 0; enable = 1; loadbit = 0; load = 12'b000000000000; enable1 = 1;
  #1  reset = 0; enable = 1; loadbit = 0; load = 12'b000000000000; enable1 = 1;
  #1  reset = 0; enable = 1; loadbit = 0; load = 12'b000000000000; enable1 = 1;
  #1  reset = 0; enable = 1; loadbit = 0; load = 12'b000000000000; enable1 = 1;
  #1  reset = 0; enable = 1; loadbit = 0; load = 12'b000000000000; enable1 = 1;
  #1  reset = 0; enable = 1; loadbit = 0; load = 12'b000000000000; enable1 = 1;
  #1  reset = 0; enable = 1; loadbit = 0; load = 12'b000000000000; enable1 = 1;
  #1  reset = 0; enable = 1; loadbit = 0; load = 12'b000000000000; enable1 = 1;
  #1  reset = 0; enable = 1; loadbit = 0; load = 12'b000000000000; enable1 = 1;
  #1  reset = 0; enable = 1; loadbit = 0; load = 12'b000000000000; enable1 = 1;
  #1  reset = 0; enable = 1; loadbit = 0; load = 12'b000000000000; enable1 = 1;
  #1  reset = 0; enable = 1; loadbit = 0; load = 12'b000000000000; enable1 = 1;
  #1  reset = 0; enable = 1; loadbit = 0; load = 12'b000000000000; enable1 = 1;
  #1  reset = 0; enable = 1; loadbit = 0; load = 12'b000000000000; enable1 = 1;
  #1  reset = 0; enable = 1; loadbit = 0; load = 12'b000000000000; enable1 = 1;
  #1  reset = 0; enable = 1; loadbit = 0; load = 12'b000000000000; enable1 = 1;
  #1  reset = 0; enable = 1; loadbit = 0; load = 12'b000000000000; enable1 = 1;
  #1  reset = 0; enable = 1; loadbit = 0; load = 12'b000000000000; enable1 = 1;
  #1  reset = 0; enable = 1; loadbit = 0; load = 12'b000000000000; enable1 = 1;
  #1  reset = 0; enable = 1; loadbit = 0; load = 12'b000000000000; enable1 = 1;
  #1  reset = 0; enable = 1; loadbit = 0; load = 12'b000000000000; enable1 = 1;
  #1  reset = 0; enable = 1; loadbit = 0; load = 12'b000000000000; enable1 = 1;
  #1  reset = 0; enable = 1; loadbit = 0; load = 12'b000000000000; enable1 = 1;
  #1  reset = 0; enable = 1; loadbit = 0; load = 12'b000000000000; enable1 = 1;
  #1  reset = 0; enable = 1; loadbit = 0; load = 12'b000000000000; enable1 = 1;
  #1  reset = 0; enable = 1; loadbit = 0; load = 12'b000000000000; enable1 = 1;
  #1  reset = 0; enable = 1; loadbit = 0; load = 12'b000000000000; enable1 = 1;
  #1  reset = 0; enable = 1; loadbit = 0; load = 12'b000000000000; enable1 = 1;
  #1  reset = 0; enable = 1; loadbit = 0; load = 12'b000000000000; enable1 = 1;
  #1  reset = 0; enable = 1; loadbit = 0; load = 12'b000000000000; enable1 = 1;
  #1  reset = 0; enable = 1; loadbit = 0; load = 12'b000000000000; enable1 = 1;
  #1  reset = 0; enable = 1; loadbit = 0; load = 12'b000000000000; enable1 = 1;
  #1  reset = 0; enable = 1; loadbit = 0; load = 12'b000000000000; enable1 = 1;
  #1  reset = 0; enable = 1; loadbit = 0; load = 12'b000000000000; enable1 = 1;
  #1  reset = 0; enable = 1; loadbit = 0; load = 12'b000000000000; enable1 = 1;
  #1  reset = 0; enable = 1; loadbit = 0; load = 12'b000000000000; enable1 = 1;
  #1  reset = 0; enable = 1; loadbit = 0; load = 12'b000000000000; enable1 = 1;
  #1  reset = 0; enable = 1; loadbit = 0; load = 12'b000000000000; enable1 = 1;
  #1  reset = 0; enable = 1; loadbit = 0; load = 12'b000000000000; enable1 = 1;
  #1  reset = 0; enable = 1; loadbit = 0; load = 12'b000000000000; enable1 = 1;
  #1  reset = 0; enable = 1; loadbit = 0; load = 12'b000000000000; enable1 = 1;
  #1  reset = 0; enable = 1; loadbit = 0; load = 12'b000000000000; enable1 = 1;
  #1  reset = 0; enable = 1; loadbit = 0; load = 12'b000000000000; enable1 = 1;
  #1  reset = 0; enable = 1; loadbit = 0; load = 12'b000000000000; enable1 = 1;
  #1  reset = 0; enable = 1; loadbit = 0; load = 12'b000000000000; enable1 = 1;
  #1  reset = 0; enable = 1; loadbit = 0; load = 12'b000000000000; enable1 = 1;
  #1  reset = 0; enable = 1; loadbit = 0; load = 12'b000000000000; enable1 = 1;
  #1  reset = 0; enable = 1; loadbit = 0; load = 12'b000000000000; enable1 = 1;
  #1  reset = 0; enable = 1; loadbit = 0; load = 12'b000000000000; enable1 = 1;
  #1  reset = 0; enable = 1; loadbit = 0; load = 12'b000000000000; enable1 = 1;
  #1  reset = 0; enable = 1; loadbit = 0; load = 12'b000000000000; enable1 = 1;
  #1  reset = 0; enable = 1; loadbit = 0; load = 12'b000000000000; enable1 = 1;
  #1  reset = 0; enable = 1; loadbit = 0; load = 12'b000000000000; enable1 = 1;
  #1  reset = 0; enable = 1; loadbit = 0; load = 12'b000000000000; enable1 = 1;
  #1  reset = 0; enable = 1; loadbit = 0; load = 12'b000000000000; enable1 = 1;
  #1  reset = 0; enable = 1; loadbit = 0; load = 12'b000000000000; enable1 = 1;
  #1  reset = 0; enable = 1; loadbit = 0; load = 12'b000000000000; enable1 = 1;
  #1  reset = 0; enable = 1; loadbit = 0; load = 12'b000000000000; enable1 = 1;
  #1  reset = 0; enable = 1; loadbit = 0; load = 12'b000000000000; enable1 = 1;
  #1  reset = 0; enable = 1; loadbit = 0; load = 12'b000000000000; enable1 = 1;
  #1  reset = 0; enable = 1; loadbit = 0; load = 12'b000000000000; enable1 = 1;
  #1  reset = 0; enable = 1; loadbit = 0; load = 12'b000000000000; enable1 = 1;
  #1  reset = 0; enable = 1; loadbit = 0; load = 12'b000000000000; enable1 = 1;
  #1  reset = 0; enable = 1; loadbit = 0; load = 12'b000000000000; enable1 = 1;
  #1  reset = 0; enable = 1; loadbit = 0; load = 12'b000000000000; enable1 = 1;
  #1  reset = 0; enable = 1; loadbit = 0; load = 12'b000000000000; enable1 = 1;
  #1  reset = 0; enable = 1; loadbit = 0; load = 12'b000000000000; enable1 = 1;
  #1  reset = 0; enable = 1; loadbit = 0; load = 12'b000000000000; enable1 = 1;
  #1  reset = 0; enable = 1; loadbit = 0; load = 12'b000000000000; enable1 = 1;
  #1  reset = 0; enable = 1; loadbit = 0; load = 12'b000000000000; enable1 = 1;
  #1  reset = 0; enable = 1; loadbit = 0; load = 12'b000000000000; enable1 = 1;
  #1  reset = 0; enable = 1; loadbit = 0; load = 12'b000000000000; enable1 = 1;
  #1  reset = 0; enable = 1; loadbit = 0; load = 12'b000000000000; enable1 = 1;
  #1  reset = 0; enable = 1; loadbit = 0; load = 12'b000000000000; enable1 = 1;
  #1  reset = 0; enable = 1; loadbit = 0; load = 12'b000000000000; enable1 = 1;
  #1  reset = 0; enable = 1; loadbit = 0; load = 12'b000000000000; enable1 = 1;
  #1  reset = 0; enable = 1; loadbit = 0; load = 12'b000000000000; enable1 = 1;
  #1  reset = 0; enable = 1; loadbit = 0; load = 12'b000000000000; enable1 = 1;
  #1  reset = 0; enable = 1; loadbit = 0; load = 12'b000000000000; enable1 = 1;
  #1  reset = 0; enable = 1; loadbit = 0; load = 12'b000000000000; enable1 = 1;
  #1  reset = 0; enable = 1; loadbit = 0; load = 12'b000000000000; enable1 = 1;
  #1  reset = 0; enable = 1; loadbit = 0; load = 12'b000000000000; enable1 = 1;
  #1  reset = 0; enable = 1; loadbit = 0; load = 12'b000000000000; enable1 = 1;
  #1  reset = 0; enable = 1; loadbit = 0; load = 12'b000000000000; enable1 = 1;
  #1  reset = 0; enable = 1; loadbit = 0; load = 12'b000000000000; enable1 = 1;



end

initial
#500 $finish;
initial begin
  $dumpfile("ejercicio1_tb.vcd");
  $dumpvars(0, testbench);
end
endmodule

EJERCICIO1/ejercicio1_tb.vcd
$date
	Thu Nov 05 17:13:58 2020
$end
$version
	Icarus Verilog
$end
$timescale
	1ps
$end
$scope module testbench $end
$var wire 4 ! Y1 [3:0] $end
$var wire 4 " Y [3:0] $end
$var reg 1 # clk $end
$var reg 1 $ enable $end
$var reg 1 % enable1 $end
$var reg 12 & load [11:0] $end
$var reg 1 ' loadbit $end
$var reg 1 ( reset $end
$scope module C4 $end
$var wire 1 # clk $end
$var wire 1 $ enable $end
$var wire 12 ) enable1 [11:0] $end
$var wire 12 * load [11:0] $end
$var wire 1 ' loadbit $end
$var wire 1 ( reset $end
$var wire 4 + Y1 [3:0] $end
$var wire 4 , Y [3:0] $end
$var wire 8 - B [7:0] $end
$var wire 12 . A [11:0] $end
$scope module C1 $end
$var wire 1 # clk $end
$var wire 1 $ enable $end
$var wire 12 / load [11:0] $end
$var wire 1 ' loadbit $end
$var wire 1 ( reset $end
$var reg 12 0 cont [11:0] $end
$upscope $end
$scope module C2 $end
$var wire 12 1 A [11:0] $end
$var wire 8 2 Y [7:0] $end
$upscope $end
$scope module C3 $end
$var wire 8 3 A [7:0] $end
$var wire 1 # clk $end
$var wire 1 4 enable $end
$var wire 1 ( reset $end
$var reg 4 5 Y [3:0] $end
$var reg 4 6 Y1 [3:0] $end
$upscope $end
$upscope $end
$upscope $end
$enddefinitions $end
#0
$dumpvars
bx 6
bx 5
04
bx 3
bx 2
bx 1
bx 0
b0 /
bx .
bx -
bx ,
bx +
b0 *
b0 )
0(
0'
b0 &
0%
0$
0#
bx "
bx !
$end
#1
b0 -
b0 2
b0 3
b0 .
b0 0
b0 1
b0 "
b0 ,
b0 5
14
b1 )
1%
1$
1(
#2
0(
#5
b1 -
b1 2
b1 3
b1 .
b1 0
b1 1
b0 !
b0 +
b0 6
1#
#10
0#
#15
b10 -
b10 2
b10 3
b10 .
b10 0
b10 1
b1 "
b1 ,
b1 5
1#
#20
0#
#25
b11 -
b11 2
b11 3
b11 .
b11 0
b11 1
b10 "
b10 ,
b10 5
1#
#30
0#
#35
b100 -
b100 2
b100 3
b100 .
b100 0
b100 1
b11 "
b11 ,
b11 5
1#
#40
0#
#45
b101 -
b101 2
b101 3
b101 .
b101 0
b101 1
b100 "
b100 ,
b100 5
1#
#50
0#
#55
b111 -
b111 2
b111 3
b110 .
b110 0
b110 1
b101 "
b101 ,
b101 5
1#
#60
0#
#65
b1000 -
b1000 2
b1000 3
b111 .
b111 0
b111 1
b111 "
b111 ,
b111 5
1#
#70
0#
#75
b1001 -
b1001 2
b1001 3
b1000 .
b1000 0
b1000 1
b1000 "
b1000 ,
b1000 5
1#
#80
0#
#85
b1010 -
b1010 2
b1010 3
b1001 .
b1001 0
b1001 1
b1001 "
b1001 ,
b1001 5
1#
#90
0#
#95
b1011 -
b1011 2
b1011 3
b1010 .
b1010 0
b1010 1
b1010 "
b1010 ,
b1010 5
1#
#100
0#
#105
b1100 -
b1100 2
b1100 3
b1011 .
b1011 0
b1011 1
b1011 "
b1011 ,
b1011 5
1#
#110
0#
#115
b1101 -
b1101 2
b1101 3
b1100 .
b1100 0
b1100 1
b1100 "
b1100 ,
b1100 5
1#
#120
0#
#125
b1110 -
b1110 2
b1110 3
b1101 .
b1101 0
b1101 1
b1101 "
b1101 ,
b1101 5
1#
#130
0#
#135
b1111 -
b1111 2
b1111 3
b1110 .
b1110 0
b1110 1
b1110 "
b1110 ,
b1110 5
1#
#140
0#
#145
b10000 -
b10000 2
b10000 3
b1111 .
b1111 0
b1111 1
b1111 "
b1111 ,
b1111 5
1#
#150
0#
#155
b10001 -
b10001 2
b10001 3
b10000 .
b10000 0
b10000 1
b1 !
b1 +
b1 6
b0 "
b0 ,
b0 5
1#
#160
0#
#165
b10010 -
b10010 2
b10010 3
b10001 .
b10001 0
b10001 1
b1 "
b1 ,
b1 5
1#
#170
0#
#175
b10011 -
b10011 2
b10011 3
b10010 .
b10010 0
b10010 1
b10 "
b10 ,
b10 5
1#
#180
0#
#185
b10100 -
b10100 2
b10100 3
b10011 .
b10011 0
b10011 1
b11 "
b11 ,
b11 5
1#
#190
0#
#195
b10101 -
b10101 2
b10101 3
b10100 .
b10100 0
b10100 1
b100 "
b100 ,
b100 5
1#
#200
0#
#205
b10110 -
b10110 2
b10110 3
b10101 .
b10101 0
b10101 1
b101 "
b101 ,
b101 5
1#
#210
0#
#215
b10111 -
b10111 2
b10111 3
b10110 .
b10110 0
b10110 1
b110 "
b110 ,
b110 5
1#
#220
0#
#225
b11000 -
b11000 2
b11000 3
b10111 .
b10111 0
b10111 1
b111 "
b111 ,
b111 5
1#
#230
0#
#235
b11001 -
b11001 2
b11001 3
b11000 .
b11000 0
b11000 1
b1000 "
b1000 ,
b1000 5
1#
#240
0#
#245
bx -
bx 2
bx 3
b11001 .
b11001 0
b11001 1
b1001 "
b1001 ,
b1001 5
1#
#250
0#
#255
b11010 .
b11010 0
b11010 1
bx !
bx +
bx 6
bx "
bx ,
bx 5
1#
#260
0#
#265
b11011 .
b11011 0
b11011 1
1#
#270
0#
#275
b11100 .
b11100 0
b11100 1
1#
#280
0#
#285
b11101 .
b11101 0
b11101 1
1#
#290
0#
#295
b11110 .
b11110 0
b11110 1
1#
#300
0#
#305
b11111 .
b11111 0
b11111 1
1#
#310
0#
#315
b100000 .
b100000 0
b100000 1
1#
#320
0#
#325
b100001 .
b100001 0
b100001 1
1#
#330
0#
#335
b100010 .
b100010 0
b100010 1
1#
#340
0#
#345
b100011 .
b100011 0
b100011 1
1#
#350
0#
#355
b100100 .
b100100 0
b100100 1
1#
#360
0#
#365
b100101 .
b100101 0
b100101 1
1#
#370
0#
#375
b100110 .
b100110 0
b100110 1
1#
#380
0#
#385
b100111 .
b100111 0
b100111 1
1#
#390
0#
#395
b101000 .
b101000 0
b101000 1
1#
#400
0#
#405
b101001 .
b101001 0
b101001 1
1#
#410
0#
#415
b101010 .
b101010 0
b101010 1
1#
#420
0#
#425
b101011 .
b101011 0
b101011 1
1#
#430
0#
#435
b101100 .
b101100 0
b101100 1
1#
#440
0#
#445
b101101 .
b101101 0
b101101 1
1#
#450
0#
#455
b101110 .
b101110 0
b101110 1
1#
#460
0#
#465
b101111 .
b101111 0
b101111 1
1#
#470
0#
#475
b110000 .
b110000 0
b110000 1
1#
#480
0#
#485
b110001 .
b110001 0
b110001 1
1#
#490
0#
#495
b110010 .
b110010 0
b110010 1
1#
